mcp_persor/__init__.py
mcp_persor/persor.py
mcp_persor/py.typed
mcp_persor/type.py
mcp_persor-1.0.6.dist-info/LICENSE
mcp_persor-1.0.6.dist-info/METADATA
mcp_persor-1.0.6.dist-info/WHEEL
mcp_persor-1.0.6.dist-info/top_level.txt
mcp_persor-1.0.6.dist-info/RECORD
