Metadata-Version: 2.1
Name: mcp-persor
Version: 1.0.6
Summary: It parses bvh files so you can easily handle them.
Home-page: https://github.com/SatooRu65536/mcp_persor
Download-URL: https://github.com/SatooRu65536/mcp_persor
Author: SatooRu
License: MIT
Requires-Python: >=3.7
License-File: LICENSE
Requires-Dist: numpy>=1.25.2
Requires-Dist: pandas>=2.0.3
Requires-Dist: matplotlib>=3.8.1
Requires-Dist: japanize-matplotlib>=1.1.3
